{
  "id": 13,
  "seed": "753045228",
  "completed_at": "2026-06-17T22:06:29.756265+00:00",
  "mode": "bijection",
  "dims": [
    "shape",
    "color",
    "texture"
  ],
  "n_kinds": {
    "shape": 5,
    "color": 5,
    "texture": 5
  },
  "n_goals": 5,
  "rule_dim": "shape",
  "rule_value": "circle",
  "total_score": 4,
  "total_steps": 40,
  "log": [
    {
      "maze_idx": 0,
      "goal_idx": 0,
      "reward": 1,
      "maze_step": 1,
      "shape": "circle",
      "color": "yellow",
      "texture": "solid"
    },
    {
      "maze_idx": 1,
      "goal_idx": 4,
      "reward": 0,
      "maze_step": 6,
      "shape": "triangle",
      "color": "green",
      "texture": "outline"
    },
    {
      "maze_idx": 1,
      "goal_idx": 3,
      "reward": 0,
      "maze_step": 11,
      "shape": "square",
      "color": "yellow",
      "texture": "striped"
    },
    {
      "maze_idx": 1,
      "goal_idx": 2,
      "reward": 1,
      "maze_step": 19,
      "shape": "circle",
      "color": "red",
      "texture": "solid"
    },
    {
      "maze_idx": 2,
      "goal_idx": 2,
      "reward": 1,
      "maze_step": 11,
      "shape": "circle",
      "color": "green",
      "texture": "striped"
    },
    {
      "maze_idx": 3,
      "goal_idx": 4,
      "reward": 1,
      "maze_step": 9,
      "shape": "circle",
      "color": "red",
      "texture": "chevron"
    }
  ],
  "mazes": [
    {
      "grid": [
        [
          1,
          1,
          1,
          1,
          1,
          1,
          1,
          1,
          1,
          1,
          1,
          1,
          1
        ],
        [
          1,
          0,
          0,
          0,
          0,
          0,
          1,
          0,
          0,
          0,
          0,
          0,
          1
        ],
        [
          1,
          0,
          0,
          0,
          0,
          0,
          0,
          0,
          0,
          0,
          0,
          0,
          1
        ],
        [
          1,
          0,
          0,
          0,
          0,
          0,
          1,
          0,
          0,
          0,
          0,
          0,
          1
        ],
        [
          1,
          0,
          0,
          0,
          0,
          0,
          1,
          0,
          0,
          0,
          0,
          0,
          1
        ],
        [
          1,
          0,
          0,
          0,
          0,
          0,
          1,
          0,
          0,
          0,
          0,
          0,
          1
        ],
        [
          1,
          1,
          0,
          1,
          1,
          1,
          1,
          1,
          1,
          0,
          1,
          1,
          1
        ],
        [
          1,
          0,
          0,
          0,
          0,
          0,
          1,
          0,
          0,
          0,
          0,
          0,
          1
        ],
        [
          1,
          0,
          0,
          0,
          0,
          0,
          1,
          0,
          0,
          0,
          0,
          0,
          1
        ],
        [
          1,
          0,
          0,
          0,
          0,
          0,
          0,
          0,
          0,
          0,
          0,
          0,
          1
        ],
        [
          1,
          0,
          0,
          0,
          0,
          0,
          1,
          0,
          0,
          0,
          0,
          0,
          1
        ],
        [
          1,
          0,
          0,
          0,
          0,
          0,
          1,
          0,
          0,
          0,
          0,
          0,
          1
        ],
        [
          1,
          1,
          1,
          1,
          1,
          1,
          1,
          1,
          1,
          1,
          1,
          1,
          1
        ]
      ],
      "agent_pos": [
        3,
        5
      ],
      "goal_positions": [
        [
          3,
          5
        ],
        [
          4,
          10
        ],
        [
          8,
          5
        ],
        [
          10,
          7
        ],
        [
          7,
          2
        ]
      ],
      "goals": [
        {
          "shape": "circle",
          "color": "yellow",
          "texture": "solid"
        },
        {
          "shape": "square",
          "color": "blue",
          "texture": "chevron"
        },
        {
          "shape": "triangle",
          "color": "red",
          "texture": "dotted"
        },
        {
          "shape": "star",
          "color": "green",
          "texture": "striped"
        },
        {
          "shape": "pentagon",
          "color": "purple",
          "texture": "outline"
        }
      ],
      "fixed_values": {}
    },
    {
      "grid": [
        [
          1,
          1,
          1,
          1,
          1,
          1,
          1,
          1,
          1,
          1,
          1,
          1,
          1
        ],
        [
          1,
          0,
          0,
          0,
          0,
          0,
          1,
          0,
          0,
          0,
          0,
          0,
          1
        ],
        [
          1,
          0,
          0,
          0,
          0,
          0,
          0,
          0,
          0,
          0,
          0,
          0,
          1
        ],
        [
          1,
          0,
          0,
          0,
          0,
          0,
          1,
          0,
          0,
          0,
          0,
          0,
          1
        ],
        [
          1,
          0,
          0,
          0,
          0,
          0,
          1,
          0,
          0,
          0,
          0,
          0,
          1
        ],
        [
          1,
          0,
          0,
          0,
          0,
          0,
          1,
          0,
          0,
          0,
          0,
          0,
          1
        ],
        [
          1,
          1,
          0,
          1,
          1,
          1,
          1,
          1,
          1,
          0,
          1,
          1,
          1
        ],
        [
          1,
          0,
          0,
          0,
          0,
          0,
          1,
          0,
          0,
          0,
          0,
          0,
          1
        ],
        [
          1,
          0,
          0,
          0,
          0,
          0,
          1,
          0,
          0,
          0,
          0,
          0,
          1
        ],
        [
          1,
          0,
          0,
          0,
          0,
          0,
          0,
          0,
          0,
          0,
          0,
          0,
          1
        ],
        [
          1,
          0,
          0,
          0,
          0,
          0,
          1,
          0,
          0,
          0,
          0,
          0,
          1
        ],
        [
          1,
          0,
          0,
          0,
          0,
          0,
          1,
          0,
          0,
          0,
          0,
          0,
          1
        ],
        [
          1,
          1,
          1,
          1,
          1,
          1,
          1,
          1,
          1,
          1,
          1,
          1,
          1
        ]
      ],
      "agent_pos": [
        9,
        5
      ],
      "goal_positions": [
        [
          3,
          5
        ],
        [
          4,
          11
        ],
        [
          9,
          5
        ],
        [
          11,
          11
        ],
        [
          8,
          9
        ]
      ],
      "goals": [
        {
          "shape": "pentagon",
          "color": "purple",
          "texture": "chevron"
        },
        {
          "shape": "star",
          "color": "blue",
          "texture": "dotted"
        },
        {
          "shape": "circle",
          "color": "red",
          "texture": "solid"
        },
        {
          "shape": "square",
          "color": "yellow",
          "texture": "striped"
        },
        {
          "shape": "triangle",
          "color": "green",
          "texture": "outline"
        }
      ],
      "fixed_values": {}
    },
    {
      "grid": [
        [
          1,
          1,
          1,
          1,
          1,
          1,
          1,
          1,
          1,
          1,
          1,
          1,
          1
        ],
        [
          1,
          0,
          0,
          0,
          0,
          0,
          1,
          0,
          0,
          0,
          0,
          0,
          1
        ],
        [
          1,
          0,
          0,
          0,
          0,
          0,
          0,
          0,
          0,
          0,
          0,
          0,
          1
        ],
        [
          1,
          0,
          0,
          0,
          0,
          0,
          1,
          0,
          0,
          0,
          0,
          0,
          1
        ],
        [
          1,
          0,
          0,
          0,
          0,
          0,
          1,
          0,
          0,
          0,
          0,
          0,
          1
        ],
        [
          1,
          0,
          0,
          0,
          0,
          0,
          1,
          0,
          0,
          0,
          0,
          0,
          1
        ],
        [
          1,
          1,
          0,
          1,
          1,
          1,
          1,
          1,
          1,
          0,
          1,
          1,
          1
        ],
        [
          1,
          0,
          0,
          0,
          0,
          0,
          1,
          0,
          0,
          0,
          0,
          0,
          1
        ],
        [
          1,
          0,
          0,
          0,
          0,
          0,
          1,
          0,
          0,
          0,
          0,
          0,
          1
        ],
        [
          1,
          0,
          0,
          0,
          0,
          0,
          0,
          0,
          0,
          0,
          0,
          0,
          1
        ],
        [
          1,
          0,
          0,
          0,
          0,
          0,
          1,
          0,
          0,
          0,
          0,
          0,
          1
        ],
        [
          1,
          0,
          0,
          0,
          0,
          0,
          1,
          0,
          0,
          0,
          0,
          0,
          1
        ],
        [
          1,
          1,
          1,
          1,
          1,
          1,
          1,
          1,
          1,
          1,
          1,
          1,
          1
        ]
      ],
      "agent_pos": [
        8,
        3
      ],
      "goal_positions": [
        [
          3,
          5
        ],
        [
          2,
          9
        ],
        [
          8,
          3
        ],
        [
          11,
          11
        ],
        [
          9,
          4
        ]
      ],
      "goals": [
        {
          "shape": "triangle",
          "color": "purple",
          "texture": "solid"
        },
        {
          "shape": "pentagon",
          "color": "red",
          "texture": "dotted"
        },
        {
          "shape": "circle",
          "color": "green",
          "texture": "striped"
        },
        {
          "shape": "square",
          "color": "blue",
          "texture": "chevron"
        },
        {
          "shape": "star",
          "color": "yellow",
          "texture": "outline"
        }
      ],
      "fixed_values": {}
    },
    {
      "grid": [
        [
          1,
          1,
          1,
          1,
          1,
          1,
          1,
          1,
          1,
          1,
          1,
          1,
          1
        ],
        [
          1,
          0,
          0,
          0,
          0,
          0,
          1,
          0,
          0,
          0,
          0,
          0,
          1
        ],
        [
          1,
          0,
          0,
          0,
          0,
          0,
          0,
          0,
          0,
          0,
          0,
          0,
          1
        ],
        [
          1,
          0,
          0,
          0,
          0,
          0,
          1,
          0,
          0,
          0,
          0,
          0,
          1
        ],
        [
          1,
          0,
          0,
          0,
          0,
          0,
          1,
          0,
          0,
          0,
          0,
          0,
          1
        ],
        [
          1,
          0,
          0,
          0,
          0,
          0,
          1,
          0,
          0,
          0,
          0,
          0,
          1
        ],
        [
          1,
          1,
          0,
          1,
          1,
          1,
          1,
          1,
          1,
          0,
          1,
          1,
          1
        ],
        [
          1,
          0,
          0,
          0,
          0,
          0,
          1,
          0,
          0,
          0,
          0,
          0,
          1
        ],
        [
          1,
          0,
          0,
          0,
          0,
          0,
          1,
          0,
          0,
          0,
          0,
          0,
          1
        ],
        [
          1,
          0,
          0,
          0,
          0,
          0,
          0,
          0,
          0,
          0,
          0,
          0,
          1
        ],
        [
          1,
          0,
          0,
          0,
          0,
          0,
          1,
          0,
          0,
          0,
          0,
          0,
          1
        ],
        [
          1,
          0,
          0,
          0,
          0,
          0,
          1,
          0,
          0,
          0,
          0,
          0,
          1
        ],
        [
          1,
          1,
          1,
          1,
          1,
          1,
          1,
          1,
          1,
          1,
          1,
          1,
          1
        ]
      ],
      "agent_pos": [
        3,
        8
      ],
      "goal_positions": [
        [
          5,
          4
        ],
        [
          2,
          9
        ],
        [
          8,
          5
        ],
        [
          8,
          11
        ],
        [
          3,
          8
        ]
      ],
      "goals": [
        {
          "shape": "pentagon",
          "color": "yellow",
          "texture": "striped"
        },
        {
          "shape": "star",
          "color": "purple",
          "texture": "solid"
        },
        {
          "shape": "square",
          "color": "green",
          "texture": "outline"
        },
        {
          "shape": "triangle",
          "color": "blue",
          "texture": "dotted"
        },
        {
          "shape": "circle",
          "color": "red",
          "texture": "chevron"
        }
      ],
      "fixed_values": {}
    }
  ],
  "prolific_pid": null,
  "study_id": null,
  "session_id": null
}